pjtTransfer/__init__.py
pjtTransfer/paramTransfer.py
pjtTransfer/pjtTransferDictionary.pkl
pjtTransfer-1.2.0.dist-info/LICENSE
pjtTransfer-1.2.0.dist-info/METADATA
pjtTransfer-1.2.0.dist-info/WHEEL
pjtTransfer-1.2.0.dist-info/top_level.txt
pjtTransfer-1.2.0.dist-info/RECORD
