Metadata-Version: 2.1
Name: pjtTransfer
Version: 1.2.0
Summary: Defect relation mapping
Home-page: https://github.com/jacsons8/zhenzhi/blob/main/%E6%B5%8B%E8%AF%95/data/paramTransfer.py
Author: hsy
Author-email: 532848352@qq.com
License: UNKNOWN
Platform: UNKNOWN
Classifier: Environment :: Web Environment
Classifier: Intended Audience :: Developers
Classifier: Operating System :: OS Independent
Classifier: Topic :: Text Processing :: Indexing
Classifier: Topic :: Utilities
Classifier: Topic :: Internet
Classifier: Topic :: Software Development :: Libraries :: Python Modules
Classifier: Programming Language :: Python
Classifier: Programming Language :: Python :: 3.7
Classifier: Programming Language :: Python :: 3.8
Classifier: Programming Language :: Python :: 3.9
